pyaxencoapi/__init__.py
pyaxencoapi/api.py
pyaxencoapi/utils.py
pyaxencoapi-1.0.4.dist-info/licenses/LICENSE
pyaxencoapi-1.0.4.dist-info/METADATA
pyaxencoapi-1.0.4.dist-info/WHEEL
pyaxencoapi-1.0.4.dist-info/top_level.txt
pyaxencoapi-1.0.4.dist-info/RECORD
